peako.py
pyPEAKO-0.0.2.post2.dist-info/LICENSE.txt
pyPEAKO-0.0.2.post2.dist-info/METADATA
pyPEAKO-0.0.2.post2.dist-info/WHEEL
pyPEAKO-0.0.2.post2.dist-info/top_level.txt
pyPEAKO-0.0.2.post2.dist-info/RECORD
