Metadata-Version: 2.1
Name: pyPEAKO
Version: 0.0.2.post2
Summary: peak detection in cloud radar Doppler spectra
Home-page: https://github.com/ti-vo/pyPEAKO
Author: Teresa Vogl
Author-email: teresa.vogl@uni-leipzig.de
License: MIT
Platform: UNKNOWN
Classifier: Programming Language :: Python :: 3.6
Classifier: License :: OSI Approved :: MIT License
Classifier: Operating System :: OS Independent
Classifier: Intended Audience :: Science/Research
Classifier: Topic :: Scientific/Engineering
Requires-Python: >=3.6
Requires-Dist: numpy (>=1.16)
Requires-Dist: scipy (>=1.2)
Requires-Dist: netCDF4 (>=1.4.2)
Requires-Dist: matplotlib (>=3.0.2)
Requires-Dist: xarray
Provides-Extra: dev
Requires-Dist: pytest (>=3.7) ; extra == 'dev'
Requires-Dist: check-manifest ; extra == 'dev'
Requires-Dist: twine ; extra == 'dev'
